{
  "artifacts": {
    "documentation": {
      "audience": "students ages 10-15, still useful for older learners",
      "bus_explanations": [],
      "buses": {},
      "control_explanations": [],
      "controls": [],
      "key_points": [
        "Connect power before testing signal pins.",
        "Default simulator delay is 15 ns; timed mode uses path-specific datasheet delays."
      ],
      "overview": "74HC166 is a 16-pin DIP part for register.",
      "part": "74HC166",
      "pin_count": 16,
      "pin_summary": {
        "input": {
          "count": 13,
          "names": [
            "SER",
            "A",
            "B",
            "C",
            "D",
            "CLK INH",
            "CLK",
            "/CLR",
            "H",
            "G",
            "F",
            "E",
            "/SH/LD"
          ],
          "note": "Input pins: SER, A, B, C, D, CLK INH, and 7 more."
        },
        "output": {
          "count": 1,
          "names": [
            "QH"
          ],
          "note": "Output pins: QH."
        },
        "power": {
          "count": 2,
          "names": [
            "GND",
            "VCC"
          ],
          "note": "Power pins: GND, VCC."
        }
      },
      "schema": "db.component.generated.documentation",
      "sections": [
        "overview",
        "pins",
        "controls",
        "truth_table",
        "timing",
        "try_it"
      ],
      "summary": "8-Bit Parallel-Load Shift Register.",
      "timing_note": "Default simulator delay is 15 ns; timed mode uses path-specific datasheet delays.",
      "title": "8-Bit Parallel-Load Shift Register",
      "version": 1
    },
    "interactive_demo": {
      "control_labels": [
        {
          "explanation": "SER controls input. Use 1 to turn this control on.",
          "hint": "Use 1 to turn this control on.",
          "label": "SER - input",
          "pin": "SER"
        },
        {
          "explanation": "A controls input. Use 1 to turn this control on.",
          "hint": "Use 1 to turn this control on.",
          "label": "A - input",
          "pin": "A"
        },
        {
          "explanation": "B controls input. Use 1 to turn this control on.",
          "hint": "Use 1 to turn this control on.",
          "label": "B - input",
          "pin": "B"
        },
        {
          "explanation": "C controls input. Use 1 to turn this control on.",
          "hint": "Use 1 to turn this control on.",
          "label": "C - input",
          "pin": "C"
        },
        {
          "explanation": "D controls input. Use 1 to turn this control on.",
          "hint": "Use 1 to turn this control on.",
          "label": "D - input",
          "pin": "D"
        },
        {
          "explanation": "CLK INH controls input. Use 1 to turn this control on.",
          "hint": "Use 1 to turn this control on.",
          "label": "CLK INH - input",
          "pin": "CLK INH"
        },
        {
          "explanation": "CLK controls input. Use 1 to turn this control on.",
          "hint": "Use 1 to turn this control on.",
          "label": "CLK - input",
          "pin": "CLK"
        },
        {
          "explanation": "/CLR controls input. This is active low, so 0 turns the control on.",
          "hint": "This is active low, so 0 turns the control on.",
          "label": "/CLR - input",
          "pin": "/CLR"
        },
        {
          "explanation": "H controls input. Use 1 to turn this control on.",
          "hint": "Use 1 to turn this control on.",
          "label": "H - input",
          "pin": "H"
        },
        {
          "explanation": "G controls input. Use 1 to turn this control on.",
          "hint": "Use 1 to turn this control on.",
          "label": "G - input",
          "pin": "G"
        },
        {
          "explanation": "F controls input. Use 1 to turn this control on.",
          "hint": "Use 1 to turn this control on.",
          "label": "F - input",
          "pin": "F"
        },
        {
          "explanation": "E controls input. Use 1 to turn this control on.",
          "hint": "Use 1 to turn this control on.",
          "label": "E - input",
          "pin": "E"
        },
        {
          "explanation": "/SH/LD controls input. This is active low, so 0 turns the control on.",
          "hint": "This is active low, so 0 turns the control on.",
          "label": "/SH/LD - input",
          "pin": "/SH/LD"
        }
      ],
      "controls": [
        "SER",
        "A",
        "B",
        "C",
        "D",
        "CLK INH",
        "CLK",
        "/CLR",
        "H",
        "G",
        "F",
        "E",
        "/SH/LD"
      ],
      "default_steps": [
        "apply controls",
        "settle",
        "probe"
      ],
      "guided_steps": [
        "Set each control to the value you want to test.",
        "Run one settle step so the simulated signals can update.",
        "Read the probes and compare them with the truth table."
      ],
      "intro": "Change the inputs, let the model settle, then read the probes.",
      "part": "74HC166",
      "probe_labels": [
        {
          "hint": "Read this output after the settle step.",
          "label": "QH",
          "name": "QH"
        }
      ],
      "probes": [
        "QH"
      ],
      "schema": "db.component.generated.interactive_demo",
      "student_questions": [
        "What changes on the probes when you flip one input?",
        "What happens when you change SER?",
        "Which truth-table row matches the value on QH?"
      ],
      "title": "Try 74HC166 in the simulator",
      "version": 1
    },
    "json": {
      "buses": {},
      "family": "74HC",
      "format": "components.generated.detail",
      "group": "74xx",
      "logic": {
        "description": "8-Bit Parallel-Load Shift Register",
        "type": "8_bit_parallel_load_shift_register"
      },
      "package": {
        "default": "N",
        "kind": "DIP",
        "pins": 16
      },
      "part": "74HC166",
      "pins": [
        {
          "direction": "input",
          "name": "SER",
          "number": 1
        },
        {
          "direction": "input",
          "name": "A",
          "number": 2
        },
        {
          "direction": "input",
          "name": "B",
          "number": 3
        },
        {
          "direction": "input",
          "name": "C",
          "number": 4
        },
        {
          "direction": "input",
          "name": "D",
          "number": 5
        },
        {
          "direction": "input",
          "name": "CLK INH",
          "number": 6
        },
        {
          "direction": "input",
          "name": "CLK",
          "number": 7
        },
        {
          "direction": "power",
          "name": "GND",
          "number": 8,
          "rail": "GND"
        },
        {
          "active_low": true,
          "direction": "input",
          "name": "/CLR",
          "number": 9
        },
        {
          "direction": "input",
          "name": "H",
          "number": 10
        },
        {
          "direction": "input",
          "name": "G",
          "number": 11
        },
        {
          "direction": "input",
          "name": "F",
          "number": 12
        },
        {
          "direction": "input",
          "name": "E",
          "number": 13
        },
        {
          "active_low": true,
          "direction": "input",
          "name": "/SH/LD",
          "number": 14
        },
        {
          "direction": "output",
          "name": "QH",
          "number": 15
        },
        {
          "direction": "power",
          "name": "VCC",
          "number": 16,
          "rail": "VCC"
        }
      ],
      "power": [
        {
          "name": "GND",
          "nominal_logic": 0,
          "pin": 8
        },
        {
          "name": "VCC",
          "nominal_logic": 1,
          "pin": 16
        }
      ],
      "role": "register",
      "timing": {
        "datasheet": {
          "conditions": "TI SN74HC166 switching characteristics, CL=50 pF, VCC=4.5 V.",
          "status": "datasheet-backed",
          "values": {
            "datasheet_fmax_mhz": {
              "sn54_min": 21,
              "sn74_min": 21,
              "typical": 31
            },
            "datasheet_max_ns_25c": {
              "clear_to_q": 24,
              "clock_to_q": 30,
              "transition": 15
            },
            "datasheet_max_ns_minus40_to_125c": {
              "clear_to_q": 36,
              "clock_to_q": 45,
              "transition": 22
            },
            "datasheet_typical_ns": {
              "clear_to_q": 18,
              "clock_to_q": 15,
              "transition": 8
            }
          }
        },
        "delay_ns": 15,
        "simple": {
          "default_delay_ns": 15,
          "source": "legacy functional simulator default"
        },
        "timed": {
          "paths": {
            "async_control_to_output_ns": {
              "condition": "async control asserted or released",
              "from": "asynchronous control",
              "parameter": "tremap",
              "ranges_ns": {
                "conservative_default": {
                  "max_ns": 15,
                  "min_ns": null,
                  "source": "conservative_default_from_existing_model_delay",
                  "typ_ns": 15
                }
              },
              "to": "Q/output"
            },
            "clock_to_output_ns": {
              "condition": "active clock edge",
              "from": "CLK/clock control",
              "parameter": "tco",
              "ranges_ns": {
                "conservative_default": {
                  "max_ns": 15,
                  "min_ns": null,
                  "source": "conservative_default_from_existing_model_delay",
                  "typ_ns": 15
                }
              },
              "to": "Q/output"
            },
            "input_setup_margin_ns": {
              "condition": "conservative setup placeholder from model delay",
              "from": "D/input",
              "parameter": "tsu",
              "ranges_ns": {
                "conservative_default": {
                  "max_ns": 15,
                  "min_ns": null,
                  "source": "conservative_default_from_existing_model_delay",
                  "typ_ns": 15
                }
              },
              "to": "CLK/clock control"
            },
            "transition_time_ns": {
              "condition": "enabled output switches",
              "from": "output transition",
              "parameter": "tt",
              "ranges_ns": {
                "conservative_default": {
                  "max_ns": 15,
                  "min_ns": null,
                  "source": "conservative_default_from_existing_model_delay",
                  "typ_ns": 15
                }
              },
              "to": "output transition"
            }
          },
          "status": "conservative_default_until_part_specific_datasheet_timing_extracted"
        },
        "timing_parameters": {
          "basis": "normalized_from_existing_datasheet_timing",
          "conditions": {
            "load_pf": 50,
            "ta_c": 25
          },
          "parameters": {
            "clock_to_q_high": {
              "note": "Serial output QH updates on clock rising edge.",
              "source_field": "TI SN74HC166 switching characteristics tpd CLK->QH",
              "status": "exact",
              "values_ns": {
                "clock_to_qh": {
                  "max_25c": {
                    "vcc_2_v": 150,
                    "vcc_4_5_v": 30,
                    "vcc_6_v": 26
                  },
                  "max_sn54": {
                    "vcc_2_v": 225,
                    "vcc_4_5_v": 45,
                    "vcc_6_v": 38
                  },
                  "max_sn74": {
                    "vcc_2_v": 225,
                    "vcc_4_5_v": 45,
                    "vcc_6_v": 38
                  },
                  "typ_25c": {
                    "vcc_2_v": 75,
                    "vcc_4_5_v": 15,
                    "vcc_6_v": 13
                  }
                }
              }
            },
            "clock_to_q_low": {
              "note": "Includes clocked output fall and asynchronous clear-to-low propagation.",
              "source_field": "TI SN74HC166 switching characteristics tpd CLK->QH and tPHL CLR->QH",
              "status": "exact",
              "values_ns": {
                "clear_to_qh_low": {
                  "max_25c": {
                    "vcc_2_v": 120,
                    "vcc_4_5_v": 24,
                    "vcc_6_v": 20
                  },
                  "max_sn54": {
                    "vcc_2_v": 180,
                    "vcc_4_5_v": 36,
                    "vcc_6_v": 31
                  },
                  "max_sn74": {
                    "vcc_2_v": 180,
                    "vcc_4_5_v": 36,
                    "vcc_6_v": 31
                  },
                  "typ_25c": {
                    "vcc_2_v": 62,
                    "vcc_4_5_v": 18,
                    "vcc_6_v": 13
                  }
                },
                "clock_to_qh": {
                  "max_25c": {
                    "vcc_2_v": 150,
                    "vcc_4_5_v": 30,
                    "vcc_6_v": 26
                  },
                  "max_sn54": {
                    "vcc_2_v": 225,
                    "vcc_4_5_v": 45,
                    "vcc_6_v": 38
                  },
                  "max_sn74": {
                    "vcc_2_v": 225,
                    "vcc_4_5_v": 45,
                    "vcc_6_v": 38
                  },
                  "typ_25c": {
                    "vcc_2_v": 75,
                    "vcc_4_5_v": 15,
                    "vcc_6_v": 13
                  }
                }
              }
            },
            "hold": {
              "note": "Hold rows are directly listed after CLK rising edge.",
              "source_field": "TI SN74HC166 timing requirements table 5.5 th rows",
              "status": "exact",
              "values_ns": {
                "clk_inh_high_after_clk_rise_min": {
                  "vcc_2_v": 0,
                  "vcc_4_5_v": 0,
                  "vcc_6_v": 0
                },
                "data_after_clk_rise_min": {
                  "vcc_2_v": 5,
                  "vcc_4_5_v": 5,
                  "vcc_6_v": 5
                },
                "ser_after_clk_rise_min": {
                  "vcc_2_v": 5,
                  "vcc_4_5_v": 5,
                  "vcc_6_v": 5
                },
                "sh_ld_high_after_clk_rise_min": {
                  "vcc_2_v": 0,
                  "vcc_4_5_v": 0,
                  "vcc_6_v": 0
                }
              }
            },
            "minimum_pulse_width": {
              "note": "Pulse duration rows explicitly cover CLR low and CLK high or low.",
              "source_field": "TI SN74HC166 timing requirements table 5.5 tw rows",
              "status": "exact",
              "values_ns": {
                "clear_low_min": {
                  "vcc_2_v": {
                    "sn54": 150,
                    "sn74": 125,
                    "ta_25c": 100
                  },
                  "vcc_4_5_v": {
                    "sn54": 30,
                    "sn74": 25,
                    "ta_25c": 20
                  },
                  "vcc_6_v": {
                    "sn54": 26,
                    "sn74": 21,
                    "ta_25c": 17
                  }
                },
                "clock_high_or_low_min": {
                  "vcc_2_v": {
                    "sn54": 120,
                    "sn74": 100,
                    "ta_25c": 80
                  },
                  "vcc_4_5_v": {
                    "sn54": 24,
                    "sn74": 20,
                    "ta_25c": 16
                  },
                  "vcc_6_v": {
                    "sn54": 20,
                    "sn74": 17,
                    "ta_25c": 14
                  }
                }
              }
            },
            "setup": {
              "note": "All setup rows are named in TI table 5.5.",
              "source_field": "TI SN74HC166 timing requirements table 5.5 tsu rows",
              "status": "exact",
              "values_ns": {
                "clear_inactive_before_clk_rise_min": {
                  "vcc_2_v": {
                    "sn54": 60,
                    "sn74": 50,
                    "ta_25c": 40
                  },
                  "vcc_4_5_v": {
                    "sn54": 12,
                    "sn74": 10,
                    "ta_25c": 8
                  },
                  "vcc_6_v": {
                    "sn54": 10,
                    "sn74": 9,
                    "ta_25c": 7
                  }
                },
                "clk_inh_low_before_clk_rise_min": {
                  "vcc_2_v": {
                    "sn54": 150,
                    "sn74": 125,
                    "ta_25c": 100
                  },
                  "vcc_4_5_v": {
                    "sn54": 30,
                    "sn74": 25,
                    "ta_25c": 20
                  },
                  "vcc_6_v": {
                    "sn54": 26,
                    "sn74": 21,
                    "ta_25c": 17
                  }
                },
                "data_before_clk_rise_min": {
                  "vcc_2_v": {
                    "sn54": 120,
                    "sn74": 100,
                    "ta_25c": 80
                  },
                  "vcc_4_5_v": {
                    "sn54": 24,
                    "sn74": 20,
                    "ta_25c": 16
                  },
                  "vcc_6_v": {
                    "sn54": 20,
                    "sn74": 17,
                    "ta_25c": 14
                  }
                },
                "ser_before_clk_rise_min": {
                  "vcc_2_v": {
                    "sn54": 120,
                    "sn74": 100,
                    "ta_25c": 80
                  },
                  "vcc_4_5_v": {
                    "sn54": 24,
                    "sn74": 20,
                    "ta_25c": 16
                  },
                  "vcc_6_v": {
                    "sn54": 20,
                    "sn74": 17,
                    "ta_25c": 14
                  }
                },
                "sh_ld_high_before_clk_rise_min": {
                  "vcc_2_v": {
                    "sn54": 220,
                    "sn74": 180,
                    "ta_25c": 145
                  },
                  "vcc_4_5_v": {
                    "sn54": 44,
                    "sn74": 36,
                    "ta_25c": 29
                  },
                  "vcc_6_v": {
                    "sn54": 38,
                    "sn74": 31,
                    "ta_25c": 25
                  }
                }
              }
            },
            "tPHL": {
              "note": "Clear-to-QH low is explicit tPHL; clock-to-QH tpd covers clocked output propagation.",
              "source_field": "TI SN74HC166 switching characteristics tPHL CLR->QH and tpd CLK->QH",
              "status": "exact",
              "values_ns": {
                "clear_to_qh_low": {
                  "max_25c": {
                    "vcc_2_v": 120,
                    "vcc_4_5_v": 24,
                    "vcc_6_v": 20
                  },
                  "max_sn54": {
                    "vcc_2_v": 180,
                    "vcc_4_5_v": 36,
                    "vcc_6_v": 31
                  },
                  "max_sn74": {
                    "vcc_2_v": 180,
                    "vcc_4_5_v": 36,
                    "vcc_6_v": 31
                  },
                  "typ_25c": {
                    "vcc_2_v": 62,
                    "vcc_4_5_v": 18,
                    "vcc_6_v": 13
                  }
                },
                "clock_to_qh": {
                  "max_25c": {
                    "vcc_2_v": 150,
                    "vcc_4_5_v": 30,
                    "vcc_6_v": 26
                  },
                  "max_sn54": {
                    "vcc_2_v": 225,
                    "vcc_4_5_v": 45,
                    "vcc_6_v": 38
                  },
                  "max_sn74": {
                    "vcc_2_v": 225,
                    "vcc_4_5_v": 45,
                    "vcc_6_v": 38
                  },
                  "typ_25c": {
                    "vcc_2_v": 75,
                    "vcc_4_5_v": 15,
                    "vcc_6_v": 13
                  }
                }
              }
            },
            "tPHZ": {
              "reason": "This clocked package has push-pull outputs and no output-enable/high-Z control.",
              "status": "not_applicable"
            },
            "tPLH": {
              "note": "CLK-to-QH tpd is the TI clocked output propagation path; CLR is only tPHL.",
              "source_field": "TI SN74HC166 switching characteristics tpd CLK->QH",
              "status": "exact",
              "values_ns": {
                "clock_to_qh": {
                  "max_25c": {
                    "vcc_2_v": 150,
                    "vcc_4_5_v": 30,
                    "vcc_6_v": 26
                  },
                  "max_sn54": {
                    "vcc_2_v": 225,
                    "vcc_4_5_v": 45,
                    "vcc_6_v": 38
                  },
                  "max_sn74": {
                    "vcc_2_v": 225,
                    "vcc_4_5_v": 45,
                    "vcc_6_v": 38
                  },
                  "typ_25c": {
                    "vcc_2_v": 75,
                    "vcc_4_5_v": 15,
                    "vcc_6_v": 13
                  }
                }
              }
            },
            "tPLZ": {
              "reason": "This clocked package has push-pull outputs and no output-enable/high-Z control.",
              "status": "not_applicable"
            },
            "tPZH": {
              "reason": "This clocked package has push-pull outputs and no output-enable/high-Z control.",
              "status": "not_applicable"
            },
            "tPZL": {
              "reason": "This clocked package has push-pull outputs and no output-enable/high-Z control.",
              "status": "not_applicable"
            }
          },
          "schema": "db.component.timing_parameters",
          "version": 1
        }
      },
      "title": "8-Bit Parallel-Load Shift Register"
    },
    "kicad_symbol": {
      "bus_groups": {},
      "labels": {
        "1": "SER",
        "10": "H",
        "11": "G",
        "12": "F",
        "13": "E",
        "14": "/SH/LD",
        "16": "VCC",
        "2": "A",
        "3": "B",
        "4": "C",
        "5": "D",
        "6": "CLK INH",
        "7": "CLK",
        "8": "GND",
        "9": "/CLR"
      },
      "left": [
        1,
        2,
        3,
        4,
        5,
        6,
        7,
        8
      ],
      "part": "74HC166",
      "pins": 16,
      "right": [
        16,
        15,
        14,
        13,
        12,
        11,
        10,
        9
      ],
      "schema": "db.component.symbol.dip",
      "shape": "dip",
      "version": 1
    },
    "python_simulator": {
      "class": "HC166",
      "copy_with_chip": [
        "DB/74xx/74HC166/simulation/model.py",
        "python/chiplib/core.py"
      ],
      "factory": "create",
      "file": "DB/74xx/74HC166/simulation/model.py",
      "part": "74HC166",
      "portable": true
    },
    "svg_pinout": {
      "bus_groups": {},
      "labels": {
        "1": "SER",
        "10": "H",
        "11": "G",
        "12": "F",
        "13": "E",
        "14": "/SH/LD",
        "16": "VCC",
        "2": "A",
        "3": "B",
        "4": "C",
        "5": "D",
        "6": "CLK INH",
        "7": "CLK",
        "8": "GND",
        "9": "/CLR"
      },
      "left": [
        1,
        2,
        3,
        4,
        5,
        6,
        7,
        8
      ],
      "part": "74HC166",
      "pins": 16,
      "right": [
        16,
        15,
        14,
        13,
        12,
        11,
        10,
        9
      ],
      "schema": "db.component.symbol.dip",
      "shape": "dip",
      "version": 1
    },
    "unit_test": {
      "part": "74HC166",
      "required_vectors": [
        "basic_function"
      ],
      "schema": "db.component.generated.tests",
      "split_records": {
        "bus_fight": {
          "applicable": false,
          "checks": [],
          "present": true,
          "reason": "bus_fight is not applicable to 74HC166",
          "source": "tests/bus_fight.json"
        },
        "propagation": {
          "applicable": true,
          "checks": [
            "model_propagation",
            "clock_to_output_metadata",
            "async_control_to_output_metadata",
            "input_setup_margin_metadata",
            "transition_time_metadata"
          ],
          "present": true,
          "source": "tests/propagation.json"
        },
        "timing": {
          "applicable": true,
          "checks": [
            "model_delay",
            "clock_to_output_metadata",
            "async_control_to_output_metadata",
            "input_setup_margin_metadata",
            "transition_time_metadata"
          ],
          "present": true,
          "source": "tests/timing.json"
        },
        "tri_state": {
          "applicable": false,
          "checks": [],
          "present": true,
          "reason": "tri_state is not applicable to 74HC166",
          "source": "tests/tri_state.json"
        },
        "truth_table": {
          "applicable": true,
          "present": true,
          "source": "tests/truth_table.json",
          "vectors": [
            "all_inputs_low",
            "all_inputs_high",
            "alternating_inputs",
            "clocked_alternating_inputs"
          ]
        }
      },
      "tests": [
        {
          "present": true,
          "source": "tests/truth_table.json",
          "type": "truth_table"
        },
        {
          "present": true,
          "source": "tests/timing.json",
          "type": "timing"
        },
        {
          "present": true,
          "source": "tests/propagation.json",
          "type": "propagation"
        }
      ],
      "version": 1
    },
    "verilog_testbench": {
      "bench_module": "tb_generated_74hc166",
      "compile": {
        "sources": [
          "DB/74xx/74HC166/simulation/model.v"
        ],
        "standard": "g2012",
        "tool": "iverilog",
        "top": "tb_generated_74hc166"
      },
      "emitted": {
        "reason": "simple emitted bench currently supports mux and scalar vector gate records only",
        "supported": false
      },
      "module": "ttl_74hc166",
      "part": "74HC166",
      "schema": "db.component.generated.verilog_testbench",
      "split_records": {
        "bus_fight": {
          "applicable": false,
          "checks": [],
          "present": true,
          "reason": "bus_fight is not applicable to 74HC166",
          "source": "tests/bus_fight.json"
        },
        "propagation": {
          "applicable": true,
          "checks": [
            "model_propagation",
            "clock_to_output_metadata",
            "async_control_to_output_metadata",
            "input_setup_margin_metadata",
            "transition_time_metadata"
          ],
          "present": true,
          "source": "tests/propagation.json"
        },
        "timing": {
          "applicable": true,
          "checks": [
            "model_delay",
            "clock_to_output_metadata",
            "async_control_to_output_metadata",
            "input_setup_margin_metadata",
            "transition_time_metadata"
          ],
          "present": true,
          "source": "tests/timing.json"
        },
        "tri_state": {
          "applicable": false,
          "checks": [],
          "present": true,
          "reason": "tri_state is not applicable to 74HC166",
          "source": "tests/tri_state.json"
        },
        "truth_table": {
          "applicable": true,
          "present": true,
          "source": "tests/truth_table.json",
          "vectors": [
            "all_inputs_low",
            "all_inputs_high",
            "alternating_inputs",
            "clocked_alternating_inputs"
          ]
        }
      },
      "version": 1
    },
    "verilog_wrapper": {
      "export": {
        "kind": "structural_port_map",
        "output_pins": [
          15
        ],
        "ports": [
          {
            "direction": "input",
            "name": "Clear_bar",
            "pins": [
              9
            ]
          },
          {
            "direction": "input",
            "name": "ShiftLoad_bar",
            "pins": [
              14
            ]
          },
          {
            "direction": "input",
            "name": "Clk",
            "pins": [
              7
            ]
          },
          {
            "direction": "input",
            "name": "ClkInhibit",
            "pins": [
              6
            ]
          },
          {
            "direction": "input",
            "name": "Serial",
            "pins": [
              1
            ]
          },
          {
            "direction": "input",
            "name": "D",
            "pins": [
              2,
              3,
              4,
              5,
              13,
              12,
              11,
              10
            ]
          },
          {
            "direction": "output",
            "name": "QH",
            "pins": [
              15
            ]
          }
        ]
      },
      "file": "DB/74xx/74HC166/simulation/model.v",
      "module": "ttl_74hc166",
      "netlist": "DB/74xx/74HC166/simulation/netlist.json",
      "part": "74HC166"
    }
  },
  "format": "db.component.generated",
  "part": "74HC166",
  "portable_files": [
    {
      "copy_as": "model.py",
      "kind": "python_model",
      "runtime": "python",
      "source": "DB/74xx/74HC166/simulation/model.py"
    },
    {
      "copy_as": "chiplib/core.py",
      "copy_once": true,
      "kind": "python_runtime",
      "runtime": "python",
      "shared": true,
      "source": "python/chiplib/core.py"
    },
    {
      "copy_as": "model.v",
      "kind": "verilog_model",
      "runtime": "verilog",
      "source": "DB/74xx/74HC166/simulation/model.v"
    },
    {
      "copy_as": "netlist.json",
      "kind": "netlist",
      "runtime": "metadata",
      "source": "DB/74xx/74HC166/simulation/netlist.json"
    }
  ],
  "source": "DB/74xx/74HC166/definition/definition.json",
  "version": 1
}
